plyvel/__init__.py
plyvel/_plyvel.cpython-39-x86_64-linux-gnu.so
plyvel/_version.py
plyvel-1.4.0.dist-info/LICENSE.rst
plyvel-1.4.0.dist-info/METADATA
plyvel-1.4.0.dist-info/WHEEL
plyvel-1.4.0.dist-info/top_level.txt
plyvel-1.4.0.dist-info/RECORD
plyvel.libs/libleveldb-44f63a48.so.1.22.0
plyvel.libs/libsnappy-aa79ab9e.so.1.1.9
