Metadata-Version: 2.1
Name: plyvel
Version: 1.4.0
Summary: Plyvel, a fast and feature-rich Python interface to LevelDB
Home-page: https://github.com/wbolster/plyvel
Author: Wouter Bolsterlee
Author-email: wouter@bolsterl.ee
License: BSD License
Platform: UNKNOWN
Classifier: Development Status :: 5 - Production/Stable
Classifier: Intended Audience :: Developers
Classifier: Intended Audience :: Information Technology
Classifier: Intended Audience :: Science/Research
Classifier: License :: OSI Approved :: BSD License
Classifier: Operating System :: POSIX
Classifier: Programming Language :: C++
Classifier: Programming Language :: Cython
Classifier: Programming Language :: Python
Classifier: Programming Language :: Python :: 2
Classifier: Programming Language :: Python :: 3
Classifier: Topic :: Database
Classifier: Topic :: Database :: Database Engines/Servers
Classifier: Topic :: Software Development :: Libraries :: Python Modules
License-File: LICENSE.rst
